.gitignore
100-blackmagicdesign.rules
LICENSE
LICENSE-gpl3.txt
LICENSE-lgpl3.txt
README.md
meson.build
meson_options.txt
openswitcher-develop.sh
openswitcher-install.sh
proxy-full.toml
proxy-xtouch.toml
proxy.toml
publish-pypi.sh
pyhyperdeckemu.py
setup.py
test-against-hardware.py
.builds/site.yml
bmd_setup/__init__.py
bmd_setup/__main__.py
bmd_setup/bmd-setup.1.scd
bmd_setup/bmd-setup.in
bmd_setup/meson.build
bmd_setup/window.py
bmd_setup/data/meson.build
bmd_setup/data/nl.brixit.Setup.appdata.xml
bmd_setup/data/nl.brixit.Setup.desktop
bmd_setup/data/nl.brixit.Setup.svg
build-aux/nl.brixit.Setup.json
build-aux/nl.brixit.Switcher.json
build-aux/meson/postinstall.py
data/meson.build
data/nl.brixit.Switcher.appdata.xml
data/nl.brixit.Switcher.desktop
data/nl.brixit.Switcher.gschema.xml
data/nl.brixit.Switcher.svg
docs/Makefile
docs/commands.rst
docs/conf.py
docs/converters.rst
docs/fields.rst
docs/index.rst
docs/make.bat
docs/media.rst
docs/proxy.rst
docs/python.rst
docs/tcptransport.rst
docs/udptransport.rst
docs/usbtransport.rst
docs/commands/audiomixer.rst
docs/commands/camera.rst
docs/commands/encoder.rst
docs/commands/fairlightmixer.rst
docs/commands/filetransfer.rst
docs/commands/hardware.rst
docs/commands/switcher.rst
docs/fields/audiomixer.rst
docs/fields/encoder.rst
docs/fields/fairlightmixer.rst
docs/fields/filetransfer.rst
docs/fields/hardware.rst
docs/fields/switcher.rst
docs/images/proxy-status.png
examples/apiserver.py
examples/cli.py
examples/stills.py
gtk_switcher/__init__.py
gtk_switcher/__main__.py
gtk_switcher/adjustmententry.py
gtk_switcher/atem.gresource.xml
gtk_switcher/atemwindow.py
gtk_switcher/audio.py
gtk_switcher/camera.py
gtk_switcher/colorwheel.py
gtk_switcher/connectionwindow.py
gtk_switcher/debugger.py
gtk_switcher/decorators.py
gtk_switcher/dial.py
gtk_switcher/downstreamkey.py
gtk_switcher/eqcurve.py
gtk_switcher/eqwindow.py
gtk_switcher/gtklogadjustment.py
gtk_switcher/layout.py
gtk_switcher/macroeditor.py
gtk_switcher/media.py
pyatem.egg-info/PKG-INFO
pyatem.egg-info/SOURCES.txt
pyatem.egg-info/dependency_links.txt
pyatem.egg-info/top_level.txt
